django_admin_oauth_sessions/__init__.py
django_admin_oauth_sessions/admin.py
django_admin_oauth_sessions/apps.py
django_admin_oauth_sessions/backends.py
django_admin_oauth_sessions/constants.py
django_admin_oauth_sessions/django_admin_oauth_sessions.py
django_admin_oauth_sessions/models.py
django_admin_oauth_sessions/tests.py
django_admin_oauth_sessions/urls.py
django_admin_oauth_sessions/utils.py
django_admin_oauth_sessions/views.py
django_admin_oauth_sessions-0.1.5.dist-info/AUTHORS.rst
django_admin_oauth_sessions-0.1.5.dist-info/LICENSE
django_admin_oauth_sessions-0.1.5.dist-info/METADATA
django_admin_oauth_sessions-0.1.5.dist-info/WHEEL
django_admin_oauth_sessions-0.1.5.dist-info/top_level.txt
django_admin_oauth_sessions-0.1.5.dist-info/RECORD
