Metadata-Version: 2.1
Name: django-admin-oauth-sessions
Version: 0.1.5
Summary: A django Project for custom authentication for sso tokens
Home-page: https://github.com/samyakjain224/django_admin_oauth_sessions
Author: Samyak Jain
Author-email: samyak.jain@agrevolution.in
License: BSD license
Keywords: django_admin_oauth_sessions
Platform: UNKNOWN
Classifier: Development Status :: 2 - Pre-Alpha
Classifier: Intended Audience :: Developers
Classifier: License :: OSI Approved :: BSD License
Classifier: Natural Language :: English
Classifier: Programming Language :: Python :: 3
Classifier: Programming Language :: Python :: 3.6
Classifier: Programming Language :: Python :: 3.7
Classifier: Programming Language :: Python :: 3.8
Requires-Python: >=3.6
License-File: LICENSE
License-File: AUTHORS.rst
Requires-Dist: Django (>=3.1)
Requires-Dist: django-allauth (~=0.45.0)
